latex_suite/__init__.py
latex_suite/bash_print.py
latex_suite/bibliography.py
latex_suite/git.py
latex_suite/latex.py
latex_suite/latex_suite.py
latex_suite/search_language_errors.py
latex_suite/util.py
latexsuite-0.9.5.dist-info/LICENSE.md
latexsuite-0.9.5.dist-info/METADATA
latexsuite-0.9.5.dist-info/WHEEL
latexsuite-0.9.5.dist-info/entry_points.txt
latexsuite-0.9.5.dist-info/top_level.txt
latexsuite-0.9.5.dist-info/RECORD
