Metadata-Version: 2.1
Name: latexsuite
Version: 0.9.5
Summary: Support your bash needs when working with latex projects in git repositories.
Home-page: https://github.com/jbuerman/latexsuite
Author: Jan Buermann
License: MIT
Classifier: License :: OSI Approved :: MIT License
Classifier: Programming Language :: Python
Classifier: Programming Language :: Python :: 3
Requires-Python: >=3.6
License-File: LICENSE.md
Requires-Dist: pyyaml
Requires-Dist: argcomplete
Requires-Dist: pybtex
